qt_remote_commands_over_ssh_for_napari_plugins/__init__.py
qt_remote_commands_over_ssh_for_napari_plugins/client.py
qt_remote_commands_over_ssh_for_napari_plugins/common.py
qt_remote_commands_over_ssh_for_napari_plugins-0.2.2.dist-info/licenses/LICENSE
qt_remote_commands_over_ssh_for_napari_plugins-0.2.2.dist-info/METADATA
qt_remote_commands_over_ssh_for_napari_plugins-0.2.2.dist-info/WHEEL
qt_remote_commands_over_ssh_for_napari_plugins-0.2.2.dist-info/top_level.txt
qt_remote_commands_over_ssh_for_napari_plugins-0.2.2.dist-info/RECORD
