Metadata-Version: 2.4
Name: qt-remote-commands-over-ssh-for-napari-plugins
Version: 0.2.2
Summary: SSH JSONL messaging utilities for napari
Author-email: Peter Newstein <peternewstein@gmail.com>
License: GPL
Project-URL: Bug Tracker, https://github.com/pnewstein/qt-remote-commands-over-ssh-for-napari-plugins/issues
Project-URL: Documentation, https://github.com/pnewstein/qt-remote-commands-over-ssh-for-napari-plugins#README.md
Project-URL: Source, https://github.com/pnewstein/qt-remote-commands-over-ssh-for-napari-plugins
Classifier: Development Status :: 4 - Beta
Classifier: Intended Audience :: Developers
Classifier: Topic :: Scientific/Engineering :: Image Processing
Classifier: Programming Language :: Python :: 3 :: Only
Classifier: Programming Language :: Python :: 3.10
Classifier: Programming Language :: Python :: 3.11
Requires-Python: >=3.10
License-File: LICENSE
Provides-Extra: dev
Requires-Dist: pytest; extra == "dev"
Provides-Extra: client
Requires-Dist: PyQt5; extra == "client"
Requires-Dist: napari; extra == "client"
Dynamic: license-file
